LICENSE
MANIFEST.in
README.md
setup.py
pynata/__init__.py
pynata.egg-info/PKG-INFO
pynata.egg-info/SOURCES.txt
pynata.egg-info/dependency_links.txt
pynata.egg-info/top_level.txt
pynata/logger/__init__.py
pynata/logger/common.py
pynata/logger/handler.py
pynata/logger/logger.py