Metadata-Version: 2.1
Name: pynata
Version: 0.4.1
Summary: Python utility library
Home-page: https://gitlab.com/meister245/pynata
Author: Zsolt Mester
Author-email: contact@zsoltmester.com
Maintainer: Project Service Desk
Maintainer-email: incoming+meister245/pynata@incoming.gitlab.com
License: MPL2.0
Project-URL: Changelog, https://gitlab.com/meister245/pynata/wikis/Changelog
Project-URL: Issue tracker, https://gitlab.com/meister245/pynata/issues
Keywords: pynata utility logging
Platform: UNKNOWN
Classifier: Intended Audience :: Developers
Classifier: License :: OSI Approved :: Mozilla Public License 2.0 (MPL 2.0)
Classifier: Operating System :: OS Independent
Classifier: Programming Language :: Python
Classifier: Programming Language :: Python :: 3
Classifier: Programming Language :: Python :: 3.5
Classifier: Programming Language :: Python :: 3.6
Classifier: Programming Language :: Python :: 3.7
Classifier: Topic :: Software Development :: Libraries :: Python Modules
Requires-Python: >=3.5.2
